dis_magic/__init__.py
dis_magic-1.0.0.dist-info/METADATA
dis_magic-1.0.0.dist-info/WHEEL
dis_magic-1.0.0.dist-info/top_level.txt
dis_magic-1.0.0.dist-info/RECORD
