Metadata-Version: 2.1
Name: dis-magic
Version: 1.0.0
Summary: IPython extension allowing visualizing bytecode of cell using magic
Home-page: https://github.com/mhconradt/dis-magic
Author: Maxwell Conradt
Author-email: mhconradt@protonmail.com
License: UNKNOWN
Platform: UNKNOWN
Classifier: Programming Language :: Python :: 3
Classifier: License :: OSI Approved :: MIT License
Classifier: Operating System :: OS Independent
Requires-Python: >=3.6
Requires-Dist: IPython
